arcade_ui/__init__.py
arcade_ui/buttons.py
arcade_ui/event_map.py
arcade_ui/panel.py
arcade_ui/text_box.py
arcade_ui/text_input.py
arcade_ui/utils.py
arcade_ui/view.py
arcade_ui/widgets.py
arcade_ui/examples/__init__.py
arcade_ui/examples/leaderboard.py
arcade_ui/examples/login.py
arcade_ui/examples/todo_list.py
arcade_ui/views/__init__.py
arcade_ui/views/list_view.py
arcade_ui-0.0.2.dist-info/LICENSE
arcade_ui-0.0.2.dist-info/METADATA
arcade_ui-0.0.2.dist-info/WHEEL
arcade_ui-0.0.2.dist-info/top_level.txt
arcade_ui-0.0.2.dist-info/RECORD
