Metadata-Version: 2.1
Name: arcade-ui
Version: 0.0.2
Summary: A high-level library to create GUIs using Arcade.
Home-page: https://github.com/Den4200/arcade_ui
Author: Dennis Pham
Author-email: dennis@f1recloud.com
License: MIT
Project-URL: Source, https://github.com/Den4200/arcade_ui
Platform: UNKNOWN
Classifier: Programming Language :: Python
Classifier: Programming Language :: Python :: 3
Classifier: Programming Language :: Python :: 3 :: Only
Classifier: Programming Language :: Python :: 3.6
Classifier: Programming Language :: Python :: 3.7
Classifier: Programming Language :: Python :: 3.8
Classifier: License :: OSI Approved :: MIT License
Classifier: Operating System :: OS Independent
Classifier: Topic :: Games/Entertainment :: Arcade
Requires-Python: >=3.6
Requires-Dist: arcade (>=2.3.15)
